relnote_extractor/__init__.py
relnote_extractor/main.py
relnote_extractor/prompts.py
relnote_extractor-2025.12.22080754.dist-info/METADATA
relnote_extractor-2025.12.22080754.dist-info/WHEEL
relnote_extractor-2025.12.22080754.dist-info/top_level.txt
relnote_extractor-2025.12.22080754.dist-info/RECORD
