Metadata-Version: 2.4
Name: relnote-extractor
Version: 2025.12.22080754
Summary: Relnote-extractor parses raw update texts, extracting version, date, features, fixes, and formats into a clean, concise summary.
Author-email: relnote-extractor <hi@eugene.plus>
License: MIT
Project-URL: Homepage, https://github.com/chigwell/relnote-extractor
Requires-Python: >=3.9
Requires-Dist: langchain-llm7>=0.0.0
Requires-Dist: llmatch-messages>=0.0.0
Requires-Dist: langchain-core>=0.3.0
